minimalist/__init__.py
minimalist/img_generator.py
minimalist-0.1.0.dist-info/WHEEL
minimalist-0.1.0.dist-info/METADATA
minimalist-0.1.0.dist-info/RECORD
